multilspy/__init__.py
multilspy/language_server.py
multilspy/multilspy_config.py
multilspy/multilspy_exceptions.py
multilspy/multilspy_logger.py
multilspy/multilspy_settings.py
multilspy/multilspy_types.py
multilspy/multilspy_utils.py
multilspy/type_helpers.py
multilspy/language_servers/dart_language_server/dart_language_server.py
multilspy/language_servers/dart_language_server/initialize_params.json
multilspy/language_servers/dart_language_server/runtime_dependencies.json
multilspy/language_servers/eclipse_jdtls/eclipse_jdtls.py
multilspy/language_servers/eclipse_jdtls/initialize_params.json
multilspy/language_servers/eclipse_jdtls/runtime_dependencies.json
multilspy/language_servers/gopls/gopls.py
multilspy/language_servers/gopls/initialize_params.json
multilspy/language_servers/jedi_language_server/initialize_params.json
multilspy/language_servers/jedi_language_server/jedi_server.py
multilspy/language_servers/omnisharp/initialize_params.json
multilspy/language_servers/omnisharp/omnisharp.py
multilspy/language_servers/omnisharp/runtime_dependencies.json
multilspy/language_servers/omnisharp/workspace_did_change_configuration.json
multilspy/language_servers/rust_analyzer/initialize_params.json
multilspy/language_servers/rust_analyzer/runtime_dependencies.json
multilspy/language_servers/rust_analyzer/rust_analyzer.py
multilspy/language_servers/solargraph/initialize_params.json
multilspy/language_servers/solargraph/runtime_dependencies.json
multilspy/language_servers/solargraph/solargraph.py
multilspy/language_servers/typescript_language_server/initialize_params.json
multilspy/language_servers/typescript_language_server/runtime_dependencies.json
multilspy/language_servers/typescript_language_server/typescript_language_server.py
multilspy/lsp_protocol_handler/lsp_constants.py
multilspy/lsp_protocol_handler/lsp_requests.py
multilspy/lsp_protocol_handler/lsp_types.py
multilspy/lsp_protocol_handler/server.py
multilspy-0.0.14.dist-info/licenses/LICENSE
multilspy-0.0.14.dist-info/WHEEL
multilspy-0.0.14.dist-info/METADATA
multilspy-0.0.14.dist-info/RECORD
