Metadata-Version: 2.4
Name: multilspy
Version: 0.0.14
Summary: A language-agnostic LSP client in Python, with a library interface. Intended to be used to build applications around language servers. Currently multilspy supports language servers for Python, Rust, Java, Go, JavaScript, Ruby, C# and Dart. Originally appeared as part of Monitor-Guided Decoding (https://github.com/microsoft/monitors4codegen)
Author-email: Lakshya A Agrawal <lakshya.aagrawal@gmail.com>
Requires-Python: >=3.8, <4.0
Classifier: Programming Language :: Python :: 3
Classifier: Operating System :: OS Independent
Classifier: Development Status :: 2 - Pre-Alpha
Classifier: Topic :: Software Development
Classifier: Topic :: Text Editors :: Integrated Development Environments (IDE)
Classifier: Programming Language :: C#
Classifier: Programming Language :: Java
Classifier: Programming Language :: Python
Classifier: Programming Language :: Rust
Classifier: Programming Language :: JavaScript
Classifier: Programming Language :: Go
Classifier: Programming Language :: Ruby
License-File: LICENSE
Requires-Dist: jedi-language-server==0.41.1
Requires-Dist: requests==2.32.3
Requires-Dist: typing-extensions>=4.2.0
Requires-Dist: psutil (>=7.0.0,<8.0.0)
Project-URL: Bug Tracker, https://github.com/microsoft/multilspy/issues
Project-URL: Homepage, https://github.com/microsoft/multilspy
